tgp/__init__.py
tgp/imports.py
tgp/src.py
tgp/connect/__init__.py
tgp/connect/base_conn.py
tgp/connect/dense_conn.py
tgp/connect/dense_conn_spt.py
tgp/connect/kron_conn.py
tgp/data/__init__.py
tgp/data/collate.py
tgp/data/loaders.py
tgp/data/transforms.py
tgp/datasets/__init__.py
tgp/datasets/csbm.py
tgp/datasets/expwl1.py
tgp/datasets/graph_classification_bench.py
tgp/datasets/gset.py
tgp/datasets/multipartite_graph.py
tgp/datasets/pygsp.py
tgp/lift/__init__.py
tgp/lift/base_lift.py
tgp/mp/__init__.py
tgp/mp/gtvconv.py
tgp/poolers/__init__.py
tgp/poolers/asap.py
tgp/poolers/asym_cheeger_cut.py
tgp/poolers/bnpool.py
tgp/poolers/bnpool_sparse.py
tgp/poolers/diffpool.py
tgp/poolers/dmon.py
tgp/poolers/edge_contraction.py
tgp/poolers/graclus.py
tgp/poolers/hosc.py
tgp/poolers/just_balance.py
tgp/poolers/kmis.py
tgp/poolers/lapool.py
tgp/poolers/maxcut.py
tgp/poolers/mincut.py
tgp/poolers/ndp.py
tgp/poolers/nmf.py
tgp/poolers/nopool.py
tgp/poolers/pan.py
tgp/poolers/sag.py
tgp/poolers/topk.py
tgp/reduce/__init__.py
tgp/reduce/base_reduce.py
tgp/reduce/global_reduce.py
tgp/select/__init__.py
tgp/select/base_select.py
tgp/select/dense_select.py
tgp/select/dp_select.py
tgp/select/edge_contraction_select.py
tgp/select/graclus_select.py
tgp/select/identity_select.py
tgp/select/kmis_select.py
tgp/select/lapool_select.py
tgp/select/maxcut_select.py
tgp/select/ndp_select.py
tgp/select/nmf_select.py
tgp/select/topk_select.py
tgp/utils/__init__.py
tgp/utils/cheatsheet.py
tgp/utils/losses.py
tgp/utils/negative_edge_sampling.py
tgp/utils/ops.py
tgp/utils/signature.py
tgp/utils/typing.py
torch_geometric_pool-0.4.0.dist-info/licenses/LICENSE
torch_geometric_pool-0.4.0.dist-info/WHEEL
torch_geometric_pool-0.4.0.dist-info/METADATA
torch_geometric_pool-0.4.0.dist-info/RECORD
