Metadata-Version: 2.4
Name: torch-geometric-pool
Version: 0.4.0
Summary: The Graph Pooling library for PyTorch Geometric.
Keywords: pytorch,pytorch-geometric,geometric-deep-learning,graph-neural-networks,graph-pooling
Author-email: Filippo Maria Bianchi <filippombianchi@gmail.com>, Ivan Marisca <ivan.marisca@usi.ch>, Carlo Abate <carlo.abate@uit.no>
Requires-Python: >=3.9
License-Expression: MIT
Classifier: Development Status :: 4 - Beta
Classifier: Intended Audience :: Science/Research
Classifier: Topic :: Scientific/Engineering :: Artificial Intelligence
Classifier: Programming Language :: Python
Classifier: Programming Language :: Python :: 3.9
Classifier: Programming Language :: Python :: 3.10
Classifier: Programming Language :: Python :: 3.11
Classifier: Programming Language :: Python :: 3.12
Classifier: Programming Language :: Python :: 3 :: Only
License-File: LICENSE
Requires-Dist: numpy >=1, <3
Requires-Dist: torch >= 1.8, <3
Requires-Dist: torch_geometric >=2.6, <3
Requires-Dist: torch_scatter
Requires-Dist: torch_sparse
Requires-Dist: pre-commit ; extra == "dev"
Requires-Dist: ruff>=0.10 ; extra == "dev"
Requires-Dist: torch_geometric_pool[notebook, test, doc] ; extra == "dev"
Requires-Dist: docutils < 1 ; extra == "doc"
Requires-Dist: sphinx >= 7.0, <8 ; extra == "doc"
Requires-Dist: sphinx-design < 1 ; extra == "doc"
Requires-Dist: sphinx-copybutton < 1 ; extra == "doc"
Requires-Dist: sphinx-hoverxref < 2 ; extra == "doc"
Requires-Dist: jupyter_sphinx ; extra == "doc"
Requires-Dist: sphinx_sitemap ; extra == "doc"
Requires-Dist: myst-nb >= 1.0, <2 ; extra == "doc"
Requires-Dist: shibuya >= 2025, <2026 ; extra == "doc"
Requires-Dist: torch_geometric_pool[notebook] ; extra == "doc"
Requires-Dist: torch_cluster ; extra == "graclus"
Requires-Dist: scipy ; extra == "ndp"
Requires-Dist: scikit-learn ; extra == "nmf"
Requires-Dist: jupyter ; extra == "notebook"
Requires-Dist: matplotlib ; extra == "notebook"
Requires-Dist: scikit-learn ; extra == "notebook"
Requires-Dist: networkx ; extra == "notebook"
Requires-Dist: torch_geometric_pool[pygsp] ; extra == "notebook"
Requires-Dist: pygsp ; extra == "pygsp"
Requires-Dist: torch_geometric_pool[ndp, nmf, graclus] ; extra == "test"
Requires-Dist: pytest ; extra == "test"
Requires-Dist: coverage[toml] ; extra == "test"
Requires-Dist: pytest-cov ; extra == "test"
Project-URL: changelog, https://github.com/tgp-team/torch-geometric-pool/blob/master/CHANGELOG.md
Project-URL: documentation, https://torch-geometric-pool.readthedocs.io
Project-URL: homepage, https://torch-geometric-pool.readthedocs.io
Project-URL: repository, https://github.com/tgp-team/torch-geometric-pool.git
Provides-Extra: dev
Provides-Extra: doc
Provides-Extra: graclus
Provides-Extra: ndp
Provides-Extra: nmf
Provides-Extra: notebook
Provides-Extra: pygsp
Provides-Extra: test
